{
    "name" : "sum",
    "description" : "The program should compute the sum of all the elements of the array b and store it in s.",
    "precondition" : "n >= 0 && (A k : 0 <= k < n : b[k] = B[k])",
    "postcondition" : "s = (SUM k : 0 <= k < n : B[k])",
    "invariant" : "0 <= i <= n && (A k : 0 <= k < n : b[k] = B[k]) && s = (SUM k : 0 <= k < i : B[k])",
    "boundaryFunction" : "n - i",
    "simplifyPrefix" : "(BG_PUSH (FORALL (b i j) (AND (IMPLIES (> i j) (EQ (sum b i j) 0)) (IMPLIES (<= i j) (EQ (sum b i j) (+ (select b j) (sum b i (- j 1))))))))"
}